xsarslc/__init__.py
xsarslc/burst.py
xsarslc/config.yml
xsarslc/get_config_infos.py
xsarslc/get_test_files.py
xsarslc/interface.py
xsarslc/tools.py
xsarslc/wallpaper.py
xsarslc/processing/HR_tiles.py
xsarslc/processing/__init__.py
xsarslc/processing/deramping.py
xsarslc/processing/impulseResponse.py
xsarslc/processing/interburst.py
xsarslc/processing/intraburst.py
xsarslc/processing/xspectra.py
xsarslc/scripts/L1B_xspectra_EW_SLC_IFR.py
xsarslc/scripts/L1B_xspectra_IW_SLC_IFR.py
xsarslc/scripts/L1B_xspectra_WV_SLC_IFR.py
xsarslc/scripts/__init__.py
xsarslc/tests/test_output_names.py
xsarslc-2024.3.18.dist-info/LICENSE
xsarslc-2024.3.18.dist-info/METADATA
xsarslc-2024.3.18.dist-info/WHEEL
xsarslc-2024.3.18.dist-info/entry_points.txt
xsarslc-2024.3.18.dist-info/top_level.txt
xsarslc-2024.3.18.dist-info/RECORD
