Metadata-Version: 2.1
Name: xsarslc
Version: 2024.3.18
Summary: Python library to compute cross spectra from SAR image
Author: Frederic Nouguier
License: GPL-3.0
Keywords: SAR,wave,reseach,cross-spectra
Classifier: Programming Language :: Python :: 3
Requires-Python: >=3.9
License-File: LICENSE
Requires-Dist: xarray
Requires-Dist: numpy
Requires-Dist: netCDF4
Requires-Dist: shapely
Requires-Dist: xrft
Requires-Dist: xarray-datatree
Requires-Dist: importlib-resources
Requires-Dist: tqdm
